voicemailbox/__init__.py
voicemailbox/__main__.py
voicemailbox/animation.py
voicemailbox/app.py
voicemailbox/backlight.py
voicemailbox/email.py
voicemailbox/logging.conf
voicemailbox/logging.py
voicemailbox/player.py
voicemailbox/screens.py
voicemailbox/static/fonts/Font Awesome 5 Free-Solid-900.otf
voicemailbox/static/images/blank_background.png
voicemailbox/static/images/circle-solid-24.png
voicemailbox/static/images/play.svg
voicemailbox/static/songs/new_mail.mp3
voicemailbox/static/songs/new_mail.wav
voicemailbox/voicemail.py
voicemailbox/voicemailbox.kv
voicemailbox-0.1.5.dist-info/LICENSE.txt
voicemailbox-0.1.5.dist-info/WHEEL
voicemailbox-0.1.5.dist-info/METADATA
voicemailbox-0.1.5.dist-info/RECORD
